[
  {
    "ContainingType": "LocalidadeController",
    "Method": "GetCidades",
    "RelativePath": "api/Localidade/{estado}",
    "HttpMethod": "GET",
    "IsController": true,
    "Order": 0,
    "Parameters": [
      {
        "Name": "estado",
        "Type": "System.String",
        "IsRequired": true
      }
    ],
    "ReturnTypes": []
  },
  {
    "ContainingType": "ProjetoEntra21.Controllers.Api.MarcasController",
    "Method": "GetMarcas",
    "RelativePath": "api/marcas",
    "HttpMethod": "GET",
    "IsController": true,
    "Order": 0,
    "Parameters": [],
    "ReturnTypes": []
  }
]